{
    "TJAM Create": {        
        "prefix": "TJAMCreateTransFile",
           "body": [
             "{",
             "    \"Comment\" : \"General template\",",
             "    \"OriginalXlfFile\" : \"$OrigEngFile\",",
             "    \"PreviousTranslationsFiles\":",
             "    [",
             "        {\"Path\":\"$PrevTransFile\"}",
             "    ],",
             "    \"RemainigTranslationsCSV\"\"$CSVRemTrFile\",",
             "    \"FinalXlfFile\":\"$FinalFile\"",
             "}"
           ],
        "description": "JAM Create translation steps file"
    }
}